setup.py
archint/__init__.py
archint.egg-info/PKG-INFO
archint.egg-info/SOURCES.txt
archint.egg-info/dependency_links.txt
archint.egg-info/top_level.txt