Metadata-Version: 2.1
Name: archint
Version: 0.0.1
Summary: archint
Home-page: UNKNOWN
Author: Anish Agrawal
Author-email: your.email@example.com
License: UNKNOWN
Platform: UNKNOWN
